search_wikt/__init__.py
search_wikt/__main__.py
search_wikt/core/__init__.py
search_wikt/core/core.py
search_wikt-0.0.5.dist-info/METADATA
search_wikt-0.0.5.dist-info/WHEEL
search_wikt-0.0.5.dist-info/licenses/LICENSE
search_wikt-0.0.5.dist-info/RECORD
