Metadata-Version: 2.1
Name: search_wikt
Version: 0.0.5
Summary: A simple command-line tool for searching Wiktionary.
Author-email: lauramvx <lesbianhouse@gmx.com>
License-File: LICENSE
Keywords: CLI,Wiktionary,dictionary,etymology
Classifier: License :: OSI Approved :: MIT License
Classifier: Operating System :: OS Independent
Classifier: Programming Language :: Python :: 3
Requires-Python: >=3.7
Requires-Dist: wiktionaryparser==0.0.97
